setup.py
distributions_jcp/Binomialdistribution.py
distributions_jcp/Gaussiandistribution.py
distributions_jcp/Generaldistribution.py
distributions_jcp/__init__.py
distributions_jcp.egg-info/PKG-INFO
distributions_jcp.egg-info/SOURCES.txt
distributions_jcp.egg-info/dependency_links.txt
distributions_jcp.egg-info/not-zip-safe
distributions_jcp.egg-info/top_level.txt