Metadata-Version: 1.0
Name: distributions-jcp
Version: 0.1
Summary: Gaussian and Binomial distributions
Home-page: UNKNOWN
Author: dan
Author-email: dan@email.com
License: UNKNOWN
Platform: UNKNOWN
